clalogger/__init__.py
clalogger/_constants.py
clalogger/_core.py
clalogger/_factory.py
clalogger/formatters.py
clalogger/handlers.py
clalogger/py.typed
clalogger-0.3.1.dist-info/LICENSE
clalogger-0.3.1.dist-info/METADATA
clalogger-0.3.1.dist-info/WHEEL
clalogger-0.3.1.dist-info/top_level.txt
clalogger-0.3.1.dist-info/RECORD
