Metadata-Version: 2.1
Name: clalogger
Version: 0.3.1
Summary: Logging from class point of view, with easy config
Home-page: https://github.com/mhooreman/clalogger
Author: Michaël Hooreman
Author-email: michael@hooreman.be
License: MIT
Project-URL: Source, https://github.com/mhooreman/clalogger
Keywords: logging stacktrace caller
Platform: UNKNOWN
Classifier: Development Status :: 3 - Alpha
Classifier: Intended Audience :: Developers
Classifier: Topic :: Software Development :: Build Tools
Classifier: License :: OSI Approved :: MIT License
Classifier: Programming Language :: Python :: 3.7
Requires-Python: >=3.6
